ape_linux.py
ape_linux-0.3.5.dist-info/METADATA
ape_linux-0.3.5.dist-info/WHEEL
ape_linux-0.3.5.dist-info/entry_points.txt
ape_linux-0.3.5.dist-info/licenses/LICENSE
ape_linux-0.3.5.dist-info/RECORD
