Metadata-Version: 2.4
Name: ape-linux
Version: 0.3.5
Summary: AI for Linux commands
Project-URL: Homepage, https://github.com/sbalian/ape
Project-URL: Repository, https://github.com/sbalian/ape
Author-email: Seto Balian <seto.balian@gmail.com>
Maintainer-email: Seto Balian <seto.balian@gmail.com>
License: MIT License
License-File: LICENSE
Keywords: ai,linux,llm,openai
Classifier: Intended Audience :: Developers
Classifier: License :: OSI Approved :: MIT License
Classifier: Programming Language :: Python
Classifier: Topic :: Software Development
Requires-Python: >=3.10
Requires-Dist: openai>=1.76.0
Requires-Dist: rich>=14.0.0
Requires-Dist: typer>=0.15.2
